mangoapi/__init__.py
mangoapi/app.py
mangoapi/cli.py
mangoapi/decorators.py
mangoapi/exceptions.py
mangoapi/logging.py
mangoapi/router.py
mangoapi/serializer.py
mangoapi/utils.py
mangoapi/validators.py
mangoapi_framework-0.1.0.dist-info/licenses/LICENSE
mangoapi_framework-0.1.0.dist-info/METADATA
mangoapi_framework-0.1.0.dist-info/WHEEL
mangoapi_framework-0.1.0.dist-info/top_level.txt
mangoapi_framework-0.1.0.dist-info/RECORD
