Metadata-Version: 2.4
Name: mangoapi-framework
Version: 0.1.0
Summary: Modern lightweight framework for building async APIs on top of Django
Author-email: Leandro Carriego <leandro.carriego@mendrisoftware.com>
License: Apache-2.0
Project-URL: Homepage, https://github.com/leandrocariego/mangoapi
Project-URL: Repository, https://github.com/leandrocariego/mangoapi
Project-URL: Issues, https://github.com/leandrocariego/mangoapi/issues
Keywords: django,api,framework,fastapi,asgi,metaframework
Requires-Python: >=3.11
License-File: LICENSE
Requires-Dist: django>=4.2
Requires-Dist: pydantic>=2.0
Requires-Dist: uvicorn>=0.34.3
Requires-Dist: starlette>=0.47.0
Requires-Dist: colorlog>=6.9.0
Provides-Extra: dev
Requires-Dist: pytest; extra == "dev"
Requires-Dist: black; extra == "dev"
Requires-Dist: ruff; extra == "dev"
Requires-Dist: pre-commit; extra == "dev"
Dynamic: license-file
